ipytone/__init__.py
ipytone/_frontend.py
ipytone/_version.py
ipytone/analysis.py
ipytone/base.py
ipytone/callback.py
ipytone/channel.py
ipytone/core.py
ipytone/dynamics.py
ipytone/effect.py
ipytone/envelope.py
ipytone/event.py
ipytone/filter.py
ipytone/graph.py
ipytone/instrument.py
ipytone/observe.py
ipytone/serialization.py
ipytone/signal.py
ipytone/source.py
ipytone/transport.py
ipytone/utils.py
ipytone/labextension/package.json
ipytone/labextension/static/367.7d2ea1a518646959ac15.js
ipytone/labextension/static/480.be1ddfc39ba5d544636f.js
ipytone/labextension/static/488.5753e6f448307feab910.js
ipytone/labextension/static/488.5753e6f448307feab910.js.LICENSE.txt
ipytone/labextension/static/568.f3a0ffd66144f0685fb9.js
ipytone/labextension/static/remoteEntry.e41cd2b06af3a21c8dc3.js
ipytone/labextension/static/style.js
ipytone/labextension/static/third-party-licenses.json
ipytone/nbextension/extension.js
ipytone/nbextension/index.js
ipytone/nbextension/index.js.LICENSE.txt
ipytone/nbextension/index.js.map
ipytone/tests/__init__.py
ipytone/tests/conftest.py
ipytone/tests/test_analysis.py
ipytone/tests/test_base.py
ipytone/tests/test_channel.py
ipytone/tests/test_core.py
ipytone/tests/test_dynamics.py
ipytone/tests/test_effect.py
ipytone/tests/test_envelope.py
ipytone/tests/test_event.py
ipytone/tests/test_filter.py
ipytone/tests/test_graph.py
ipytone/tests/test_instrument.py
ipytone/tests/test_nbextension_path.py
ipytone/tests/test_observe.py
ipytone/tests/test_signal.py
ipytone/tests/test_source.py
ipytone/tests/test_transport.py
ipytone/tests/test_utils.py
ipytone-0.5.1.data/data/share/jupyter/labextensions/ipytone/package.json
ipytone-0.5.1.data/data/share/jupyter/labextensions/ipytone/static/367.7d2ea1a518646959ac15.js
ipytone-0.5.1.data/data/share/jupyter/labextensions/ipytone/static/480.be1ddfc39ba5d544636f.js
ipytone-0.5.1.data/data/share/jupyter/labextensions/ipytone/static/488.5753e6f448307feab910.js
ipytone-0.5.1.dist-info/METADATA
ipytone-0.5.1.dist-info/WHEEL
ipytone-0.5.1.dist-info/licenses/LICENSE.txt
ipytone-0.5.1.dist-info/RECORD
