Metadata-Version: 2.1
Name: ipytone
Version: 0.5.1
Summary: Interactive audio in Jupyter
Project-URL: Homepage, https://github.com/benbovy/ipytone
Author: Benoît Bovy
License: Copyright (c) 2020 Benoit Bovy
License-File: LICENSE.txt
Keywords: Audio,IPython,Jupyter,Sonification,Sound,Widgets
Classifier: Framework :: Jupyter
Classifier: License :: OSI Approved :: BSD License
Classifier: Programming Language :: Python
Classifier: Programming Language :: Python :: 3
Requires-Python: >=3.7
Requires-Dist: ipywidgets>=7.6.0
Requires-Dist: numpy
Requires-Dist: traittypes
Provides-Extra: doc
Requires-Dist: jupyterlite; extra == 'doc'
Requires-Dist: jupyterlite-sphinx; extra == 'doc'
Requires-Dist: jupyterlite-xeus-python; extra == 'doc'
Requires-Dist: matplotlib; extra == 'doc'
Requires-Dist: myst-nb; extra == 'doc'
Requires-Dist: pydata-sphinx-theme; extra == 'doc'
Requires-Dist: sphinx; extra == 'doc'
Provides-Extra: lint
Requires-Dist: black; extra == 'lint'
Provides-Extra: test
Requires-Dist: ipykernel; extra == 'test'
Requires-Dist: pytest-cov; extra == 'test'
Requires-Dist: pytest-mock; extra == 'test'
Requires-Dist: pytest>=4.6; extra == 'test'
